encab/__init__.py
encab/__main__.py
encab/config.py
encab/encab.py
encab/extensions.py
encab/program.py
encab/program_state.py
encab/programs.py
encab/common/exit_codes.py
encab/common/log_stream.py
encab/common/process.py
encab/ext/__init__.py
encab/ext/log_collector.py
encab/ext/log_sanitizer.py
encab/ext/startup_script.py
encab/ext/validation.py
encab-1.0.2.dist-info/licenses/LICENSE
encab-1.0.2.dist-info/METADATA
encab-1.0.2.dist-info/WHEEL
encab-1.0.2.dist-info/entry_points.txt
encab-1.0.2.dist-info/top_level.txt
encab-1.0.2.dist-info/RECORD
