Metadata-Version: 2.4
Name: encab
Version: 1.0.2
Summary: Process manager
Author-email: Sebastian Kuebeck <sebastian.kuebeck@encab.io>
Project-URL: Homepage, https://github.com/sebastian-kuebeck/encab
Project-URL: Documentation, https://encab.readthedocs.io
Project-URL: Bug Tracker, https://github.com/sebastian-kuebeck/encab
Classifier: Programming Language :: Python :: 3
Classifier: Programming Language :: Python :: 3.7
Classifier: Programming Language :: Python :: 3.8
Classifier: Programming Language :: Python :: 3.9
Classifier: Programming Language :: Python :: 3.10
Classifier: Programming Language :: Python :: 3.11
Classifier: Programming Language :: Python :: 3.12
Classifier: Programming Language :: Python :: 3.13
Classifier: Programming Language :: Python :: 3.14
Classifier: Programming Language :: Python :: 3.15
Classifier: License :: OSI Approved :: MIT License
Classifier: Operating System :: OS Independent
Requires-Python: >=3.7
License-File: LICENSE
Requires-Dist: PyYAML<7,>=6.0
Requires-Dist: types-PyYAML<7,>=6.0.12.2
Requires-Dist: marshmallow<5,>=3.19.0
Requires-Dist: marshmallow-dataclass[enum,union]<9,>=8.5.10
Requires-Dist: marshmallow-enum<2,>=1.5.1
Requires-Dist: pluggy<2,>=1.0.0
Requires-Dist: python-dotenv<2,>=0.21.1
Dynamic: license-file
